Metadata-Version: 2.1
Name: cyprimes
Version: 0.5.0
Summary: Module for working with prime numbers.
Home-page: https://github.com/andreas19/cyprimes/
Author: Andreas Suhre
Author-email: andreas19@posteo.eu
License: BSD-3-Clause
Platform: UNKNOWN
Classifier: Development Status :: 4 - Beta
Classifier: License :: OSI Approved :: BSD License
Classifier: Natural Language :: English
Classifier: Programming Language :: Python :: 3
Classifier: Programming Language :: Python :: 3.7
Classifier: Programming Language :: Python :: 3.8
Classifier: Programming Language :: Cython
Classifier: Topic :: Software Development :: Libraries
Requires-Python: >=3.7
